qadoc/__init__.py
qadoc/__main__.py
qadoc/qa.py
qadoc-0.1.0.dist-info/METADATA
qadoc-0.1.0.dist-info/WHEEL
qadoc-0.1.0.dist-info/entry_points.txt
qadoc-0.1.0.dist-info/RECORD
