Metadata-Version: 2.3
Name: qadoc
Version: 0.1.0
Summary: PDF-based Question Answering (Q&A) system with LangChain and OpenAI.
Keywords: q&a
Author: Sam Scott
Author-email: sam.scott7@me.com
Requires-Python: >=3.9,<4.0
Classifier: Programming Language :: Python :: 3
Classifier: Programming Language :: Python :: 3.9
Classifier: Programming Language :: Python :: 3.10
Classifier: Programming Language :: Python :: 3.11
Classifier: Programming Language :: Python :: 3.12
Classifier: Programming Language :: Python :: 3.13
Requires-Dist: click (>=8.1.8)
Requires-Dist: langchain-community (>=0.3.17)
Requires-Dist: langchain-openai (>=0.3.6)
Requires-Dist: pypdf (>=5.3.0)
